{
    "je": "is",
    "da": "that",
    "ne": "not",
    "se": "is",
    "i": "and",
    "u": "in",
    "to": "it",
    "sam": "himself",
    "što": "what",
    "na": "on",
    "ti": "you",
    "za": "for",
    "mi": "me",
    "si": "Si",
    "li": "li",
    "ja": "I",
    "su": "are",
    "ali": "but",
    "nije": "Not",
    "s": "with",
    "samo": "only",
    "ga": "him",
    "me": "me",
    "od": "from",
    "a": "And",
    "bi": "would",
    "ovo": "this",
    "kako": "how",
    "te": "you",
    "će": "will",
    "o": "on",
    "dobro": "good",
    "ako": "if",
    "smo": "we",
    "sa": "with",
    "sve": "all",
    "kao": "as",
    "ću": "I'll",
    "biti": "be",
    "tako": "so",
    "znam": "I know",
    "ste": "you are",
    "nisam": "I am not",
    "ovdje": "here",
    "bio": "was",
    "mogu": "I can",
    "pa": "and",
    "zašto": "why",
    "on": "he",
    "još": "more",
    "redu": "order",
    "bilo": "any",
    "nešto": "something",
    "kad": "when",
    "koji": "who",
    "vas": "your",
    "mislim": "I think",
    "hvala": "thank you",
    "iz": "from",
    "ili": "or",
    "možda": "maybe",
    "ih": "them",
    "gdje": "where",
    "ima": "have",
    "vam": "you",
    "više": "more",
    "znaš": "You know",
    "rekao": "said",
    "sada": "now",
    "moj": "my",
    "onda": "then",
    "bih": "BiH",
    "tko": "who",
    "mu": "him",
    "ćemo": "we will",
    "do": "to",
    "nema": "No",
    "bila": "was",
    "ništa": "nothing",
    "zar": "right",
    "nas": "our",
    "ona": "she",
    "želim": "I want to",
    "malo": "little",
    "mene": "me",
    "može": "can",
    "vi": "you",
    "molim": "I pray",
    "kada": "when",
    "reći": "say",
    "šta": "what",
    "jer": "because",
    "prije": "ago",
    "tebe": "you",
    "hej": "hey",
    "imam": "I have a",
    "možeš": "You can",
    "sad": "now",
    "tu": "here",
    "ćeš": "you will"
}
