{
    "ég": "I",
    "ađ": "a",
    "er": "which",
    "í": "in",
    "ekki": "not",
    "ūađ": "you",
    "og": "and",
    "á": "on",
    "ūú": "you",
    "viđ": "We",
    "hann": "he",
    "ūetta": "you",
    "hvađ": "what",
    "sem": "who",
    "mér": "me",
    "til": "to",
    "en": "but",
    "međ": "among",
    "ūér": "you",
    "fyrir": "by",
    "af": "of",
    "um": "of",
    "var": "was",
    "mig": "me",
    "ūig": "ūig",
    "að": "that",
    "já": "yes",
    "hún": "she",
    "nei": "no",
    "ūví": "you",
    "allt": "everything",
    "bara": "just",
    "svo": "then",
    "eru": "are",
    "ef": "if",
    "ert": "are",
    "ūá": "y",
    "það": "it",
    "ertu": "are you",
    "eins": "likewise",
    "okkur": "U.S",
    "vera": "stay",
    "lagi": "right",
    "eftir": "over",
    "gera": "do",
    "veit": "know",
    "ūiđ": "ūi",
    "hefur": "has",
    "hér": "here",
    "ūeir": "you",
    "nú": "now",
    "frá": "of",
    "fara": "leave",
    "þú": "you",
    "hvernig": "how",
    "viđ": "we",
    "út": "out",
    "ūegar": "today",
    "hef": "have",
    "upp": "up",
    "aftur": "again",
    "honum": "him",
    "svona": "thus",
    "minn": "mine",
    "ekkert": "nothing",
    "vel": "well",
    "sé": "see",
    "hana": "her",
    "verđur": "worth",
    "hver": "any",
    "þetta": "that",
    "ykkur": "you",
    "ūessu": "this",
    "vil": "want",
    "veriđ": "would be",
    "komdu": "come",
    "segja": "tell",
    "erum": "are",
    "eđa": "or",
    "hérna": "here",
    "úr": "watch",
    "get": "can",
    "hverju": "which",
    "aldrei": "never",
    "gott": "good",
    "hvar": "where",
    "hafa": "have",
    "hjá": "on",
    "getur": "can",
    "koma": "arrival",
    "okkar": "our",
    "viltu": "do you want",
    "inn": "inwards",
    "fá": "gain",
    "núna": "presently",
    "mađur": "center",
    "takk": "thanks",
    "eitthvađ": "something",
    "kannski": "perhaps",
    "hvað": "what"
  }
  