{
  "apple": "jablko",
  "orange": "pomarancza",
  "car": "samochod",
  "tree": "drzewo",
  "river": "rzeka",
  "mountain": "gora",
  "book": "ksiazka",
  "computer": "komputer",
  "sun": "slonce",
  "moon": "ksiezyc",
  "flower": "kwiat",
  "bird": "ptak",
  "fish": "ryba",
  "cloud": "chmura",
  "rain": "deszcz",
  "fire": "ogien",
  "earth": "ziemia",
  "wind": "wiatr",
  "coffee": "kawa",
  "music": "muzyka",
  "happy": "szczesliwy",
  "sad": "smutny",
  "friend": "przyjaciel",
  "love": "milosc",
  "time": "czas",
  "space": "przestrzen",
  "color": "kolor",
  "dream": "marzenie",
  "journey": "podroz",
  "word": "slowo",
  "dog": "pies",
  "cat": "kot",
  "long_sentence": "To jest zdanie majace 30 znakow."
}
